deduce_uces/Logger.py
deduce_uces/__init__.py
deduce_uces/__main__.py
deduce_uces/commands/align.py
deduce_uces/commands/extend.py
deduce_uces/commands/find.py
deduce_uces/commands/info.py
deduce_uces/commands/minimise.py
deduce_uces/extenders/extender.py
deduce_uces/extenders/minimap_extender.py
deduce_uces/io.py
deduce_uces/matchers/bowtie_matcher.py
deduce_uces/matchers/minimap_matcher.py
deduce_uces/matchers/naive_matcher.py
deduce_uces/mergers/graph_merger.py
deduce_uces/mergers/merger.py
deduce_uces/mergers/naive_merger.py
deduce_uces/output/gff.py
deduce_uces/output/output.py
deduce_uces/output/paf.py
deduce_uces/output/tsv.py
deduce_uces/types.py
deduce_uces/utils.py
deduce_uces-1.0.2.dist-info/entry_points.txt
deduce_uces-1.0.2.dist-info/LICENSE.txt
deduce_uces-1.0.2.dist-info/WHEEL
deduce_uces-1.0.2.dist-info/METADATA
deduce_uces-1.0.2.dist-info/RECORD
